{
    "parent": "block/block",
	"textures": {
		"particle": "block/bookshelf",
		"thin0": "block/books/thin/0",
        "thin1": "block/books/thin/1",
        "thin2": "block/books/thin/2",
        "thin3": "block/books/thin/3"
    },
	"elements": [
		{   "__comment": "Book1",
			"from": [ 3.25, 8.25, 0.25 ],
            "to": [ 4.25, 14.5, 3.25 ],
            "faces": {
                "up":  { "uv": [ 9.25, 7.125, 10.25, 10.125 ], "texture": "#thin0", "rotation": 180, "cullface": "north" },
                "east": { "uv": [ 1.125, 6, 4.125, 12.25 ], "texture": "#thin0", "cullface": "north" },
                "north":  { "uv": [ 4.125, 6, 5.125, 12.25 ], "texture": "#thin0", "cullface": "north" },
                "west": { "uv": [ 5.125, 6, 8.125, 12.25 ], "texture": "#thin0", "cullface": "north" }
            }
        },
        {   "__comment": "Book2",
            "from": [ 2.25, 8.25, 0 ],
            "to": [ 3.25, 13.625, 2.25 ],
            "faces": {
                "up":  { "uv": [ 8.25, 7.375, 9.25, 9.625 ], "texture": "#thin1", "rotation": 180, "cullface": "north" },
                "east": { "uv": [ 1.375, 6, 3.625, 11.375 ], "texture": "#thin1", "cullface": "north" },
                "north":  { "uv": [ 3.625, 6, 4.625, 11.375 ], "texture": "#thin1", "cullface": "north" },
                "west": { "uv": [ 4.625, 6, 6.875, 11.375 ], "texture": "#thin1", "cullface": "north" }
            }
        },
        {   "__comment": "Book3",
            "from": [ 1.125, 8.25, 0.375 ],
            "to": [ 2.25, 14.25, 1.125 ],
            "faces": {
                "up":  { "uv": [ 8.625, 9, 9.75, 9.75 ], "texture": "#thin2", "rotation": 180, "cullface": "north" },
                "east": { "uv": [ 3, 6, 3.75, 12 ], "texture": "#thin2", "cullface": "north" },
                "north":  { "uv": [ 3.75, 6, 4.875, 12 ], "texture": "#thin2", "cullface": "north" },
                "west": { "uv": [ 4.875, 6, 5.625, 12 ], "texture": "#thin2", "cullface": "north" }
            }
        },
        {   "__comment": "Book4",
            "from": [ 0.5, 8.25, 0.125 ],
            "to": [ 1.125, 13.625, 0.5 ],
            "faces": {
                "up":  { "uv": [ 8.375, 10.5, 9, 10.875 ], "texture": "#thin3", "rotation": 180, "cullface": "north" },
                "east": { "uv": [ 3.5, 7, 3.875, 12.375 ], "texture": "#thin3", "cullface": "north" },
                "north":  { "uv": [ 3.875, 7, 4.5, 12.375 ], "texture": "#thin3", "cullface": "north" }
            }
        }
    ]
}