{
    "parent": "block/block",
	"textures": {
        "wood": "block/planks_oak",
		"particle": "block/bookshelf",
		"dark": "block/bookshelf_shadow",
		"books0": "block/books/books0",
		"books1": "block/books/books1",
		"books2": "block/books/books2",
		"books3": "block/books/books3",
		"books4": "block/books/books4",
		"books5": "block/books/books5",
		"books6": "block/books/books6",
		"books7": "block/books/books7",
		"books8": "block/books/books8",
		"books9": "block/books/books9",
		"books10": "block/books/books10",
		"books11": "block/books/books11"
    },
	"elements": [
		
		{   "__comment": "Book1 Bottom North",
			"from": [ 14.75, 0.5, 0.4 ],
            "to": [ 15.5, 7.375, 4.9 ],
            "faces": {
                "north":  { "uv": [ 4.5, 0, 5.25, 6.875 ], "texture": "#books6", "cullface": "north" },
                "west": { "uv": [ 5.25, 0, 9.75, 6.875 ], "texture": "#books6", "cullface": "north" }
            }
        },
		{   "__comment": "Top of Book1 Bottom North",
			"from": [ 14.75, 0.5, 0.4 ],
            "to": [ 15.5, 7.375, 0.525 ],
            "faces": {
                "up":    { "uv": [ 14, 8, 16, 8.125 ], "texture": "#books6", "cullface": "north" }
            }
        },
		{   "__comment": "Top of Book1 Bottom North",
			"from": [ 14.75, 0.5, 0.525 ],
            "to": [ 15.375, 7.375, 0.65 ],
            "faces": {
                "up":    { "uv": [ 14, 8.125, 16, 8.25 ], "texture": "#books6", "cullface": "north" }
            }
        },
		{   "__comment": "Top of Book1 Bottom North",
			"from": [ 14.75, 0.5, 0.65 ],
            "to": [ 15.25, 7.375, 0.775 ],
            "faces": {
                "up":    { "uv": [ 14, 8.25, 16, 8.375 ], "texture": "#books6", "cullface": "north" }
            }
        },
		{   "__comment": "Top of Book1 Bottom North",
			"from": [ 14.75, 0.5, 0.775 ],
            "to": [ 15.125, 7.375, 0.9 ],
            "faces": {
                "up":    { "uv": [ 14, 8.375, 16, 8.5 ], "texture": "#books6", "cullface": "north" }
            }
        },
		{   "__comment": "Top of Book1 Bottom North",
			"from": [ 14.75, 0.5, 0.9 ],
            "to": [ 15, 7.375, 1.025 ],
            "faces": {
                "up":    { "uv": [ 14, 8.5, 16, 8.625 ], "texture": "#books6", "cullface": "north" }
            }
        },
		{   "__comment": "Top of Book1 Bottom North",
			"from": [ 14.75, 0.5, 1.025 ],
            "to": [ 14.875, 7.375, 1.15 ],
            "faces": {
                "up":    { "uv": [ 14, 8.625, 16, 8.75 ], "texture": "#books6", "cullface": "north" }
            }
        },
		{   "__comment": "Book2 Bottom North",
			"from": [ 13.25, 0.5, 0.2 ],
            "to": [ 14.5, 6.25, 1.45 ],
            "faces": {
                "up":    { "uv": [ 14, 8, 16, 9.25 ], "texture": "#books6", "cullface": "north" },
                "east": { "uv": [ 2.375, 7, 3.625, 12.75 ], "texture": "#books6", "cullface": "north" },
                "north":  { "uv": [ 3.625, 7, 4.875, 12.75 ], "texture": "#books6", "cullface": "north" },
                "west": { "uv": [ 4.875, 7, 6.125, 12.75 ], "texture": "#books6", "cullface": "north" }
            }
        }
    ]
}